tbtrim.py
tbtrim-0.3.1.dist-info/LICENSE
tbtrim-0.3.1.dist-info/METADATA
tbtrim-0.3.1.dist-info/WHEEL
tbtrim-0.3.1.dist-info/top_level.txt
tbtrim-0.3.1.dist-info/RECORD
